arrowline.py
circuitpython_ArrowLine-1.1.0.dist-info/LICENSE
circuitpython_ArrowLine-1.1.0.dist-info/METADATA
circuitpython_ArrowLine-1.1.0.dist-info/WHEEL
circuitpython_ArrowLine-1.1.0.dist-info/top_level.txt
circuitpython_ArrowLine-1.1.0.dist-info/RECORD
