Metadata-Version: 2.1
Name: circuitpython-ArrowLine
Version: 1.1.0
Summary: CircuitPython library to draw Arrowlines.
Author-email: "Jose D. Montoya" <arrowline@mailmeto.mozmail.com>
License: MIT
Project-URL: Homepage, https://github.com/jposada202020/CircuitPython_ArrowLine.git
Keywords: hardware,micropython,circuitpython
Classifier: Intended Audience :: Developers
Classifier: Topic :: Software Development :: Libraries
Classifier: Topic :: Software Development :: Embedded Systems
Classifier: Topic :: System :: Hardware
Classifier: License :: OSI Approved :: MIT License
Classifier: Programming Language :: Python :: 3
License-File: LICENSE
Requires-Dist: Adafruit-Blinka
Provides-Extra: optional
